README.txt
setup.py
collective/__init__.py
collective.recipe.symlink.egg-info/PKG-INFO
collective.recipe.symlink.egg-info/SOURCES.txt
collective.recipe.symlink.egg-info/dependency_links.txt
collective.recipe.symlink.egg-info/entry_points.txt
collective.recipe.symlink.egg-info/namespace_packages.txt
collective.recipe.symlink.egg-info/not-zip-safe
collective.recipe.symlink.egg-info/requires.txt
collective.recipe.symlink.egg-info/top_level.txt
collective/recipe/__init__.py
collective/recipe/symlink/__init__.py
docs/HISTORY.txt