Metadata-Version: 1.0
Name: collective.recipe.symlink
Version: 0.1
Summary: A recipe to create symbolic links of an egg
Home-page: http://svn.plone.org/svn/collective/
Author: Matous Hora
Author-email: matous.hora@dms4u.cz
License: GPL
Platform: UNKNOWN
Classifier: Programming Language :: Python
